odoo/addons/partner_contact_access_link/README.rst
odoo/addons/partner_contact_access_link/__init__.py
odoo/addons/partner_contact_access_link/__manifest__.py
odoo/addons/partner_contact_access_link/i18n/partner_contact_access_link.pot
odoo/addons/partner_contact_access_link/models/__init__.py
odoo/addons/partner_contact_access_link/models/res_partner.py
odoo/addons/partner_contact_access_link/readme/CONTRIBUTORS.rst
odoo/addons/partner_contact_access_link/readme/DESCRIPTION.rst
odoo/addons/partner_contact_access_link/readme/USAGE.rst
odoo/addons/partner_contact_access_link/static/description/full-form.gif
odoo/addons/partner_contact_access_link/static/description/icon.png
odoo/addons/partner_contact_access_link/static/description/index.html
odoo/addons/partner_contact_access_link/views/res_partner_views.xml
odoo13_addon_partner_contact_access_link-13.0.1.0.1.dev3.dist-info/METADATA
odoo13_addon_partner_contact_access_link-13.0.1.0.1.dev3.dist-info/WHEEL
odoo13_addon_partner_contact_access_link-13.0.1.0.1.dev3.dist-info/top_level.txt
odoo13_addon_partner_contact_access_link-13.0.1.0.1.dev3.dist-info/RECORD
