Metadata-Version: 2.1
Name: odoo13-addon-partner-contact-access-link
Version: 13.0.1.0.1.dev3
Summary: Allow to visit the full contact form from a company
Home-page: https://github.com/OCA/partner-contact
Author: Tecnativa, Odoo Community Association (OCA)
Author-email: support@odoo-community.org
License: AGPL-3
Platform: UNKNOWN
Classifier: Programming Language :: Python
Classifier: Framework :: Odoo
Classifier: Framework :: Odoo :: 13.0
Classifier: License :: OSI Approved :: GNU Affero General Public License v3
Classifier: Development Status :: 5 - Production/Stable
Requires-Python: >=3.5
Requires-Dist: odoo <13.1dev,>=13.0a
